sphinx_thrift/__init__.py
sphinx_thrift/documenter.py
sphinx_thrift/domain.py
sphinx_thrift/parser.py
sphinx_thrift/thrift_ast.py
sphinx_thrift-0.1.0.dist-info/LICENSE
sphinx_thrift-0.1.0.dist-info/WHEEL
sphinx_thrift-0.1.0.dist-info/METADATA
sphinx_thrift-0.1.0.dist-info/RECORD
