Metadata-Version: 2.1
Name: sphinx-thrift
Version: 0.1.0
Summary: 
Author: Csonkás Kristóf Gyula
Author-email: csonkas.kristof@gmail.com
Requires-Python: >=3.7,<4.0
Classifier: Programming Language :: Python :: 3
Classifier: Programming Language :: Python :: 3.7
Classifier: Programming Language :: Python :: 3.8
Classifier: Programming Language :: Python :: 3.9
Requires-Dist: sphinx (>=3.5.1,<4.0.0)
